videohub/__init__.py
videohub/client.py
videohub-0.0.3.dist-info/LICENSE
videohub-0.0.3.dist-info/METADATA
videohub-0.0.3.dist-info/WHEEL
videohub-0.0.3.dist-info/top_level.txt
videohub-0.0.3.dist-info/RECORD
